README.md
setup.cfg
setup.py
sanic_filter/__init__.py
sanic_filter/filter.py
sanic_filter.egg-info/PKG-INFO
sanic_filter.egg-info/SOURCES.txt
sanic_filter.egg-info/dependency_links.txt
sanic_filter.egg-info/not-zip-safe
sanic_filter.egg-info/top_level.txt