Metadata-Version: 2.1
Name: sanic-filter
Version: 0.0.7
Summary: Query filter for Sanic
Author-email: lolkin4777@gmail.com
Classifier: Programming Language :: Python :: 3.9
Classifier: License :: OSI Approved :: MIT License
Classifier: Operating System :: OS Independent
Requires-Python: >=3.9
